designer_cmd/__init__.py
designer_cmd/__pycache__/__init__.cpython-38.pyc
designer_cmd/__pycache__/api.cpython-38.pyc
designer_cmd/api/__init__.py
designer_cmd/api/main_executable.py
designer_cmd/api/rac_executable.py
designer_cmd/tests/__init__.py
designer_cmd/tests/__main__.py
designer_cmd/tests/test_api.py
designer_cmd/tests/test_utils.py
designer_cmd/tests/__pycache__/__init__.cpython-38.pyc
designer_cmd/tests/__pycache__/__main__.cpython-38.pyc
designer_cmd/tests/__pycache__/test_api.cpython-38.pyc
designer_cmd/tests/__pycache__/test_utils.cpython-38.pyc
designer_cmd/tests/test_data/1Cv8.cf
designer_cmd/tests/test_data/1Cv8.dt
designer_cmd/tests/test_data/1Cv8_increment.cf
designer_cmd/tests/test_data/MergeSettings.xml
designer_cmd/tests/test_data/obj_list
designer_cmd/tests/test_data/obj_list_all_objects
designer_cmd/tests/test_data/test.cfe
designer_cmd/tests/test_data/test2.cfe
designer_cmd/tests/test_data/test_epf.epf
designer_cmd/tests/test_data/wmic_data
designer_cmd/tests/test_data/base/.gitkeep
designer_cmd/tests/test_data/temp/.gitkeep
designer_cmd/utils/__init__.py
designer_cmd/utils/utils.py
designer_cmd/utils/__pycache__/__init__.cpython-38.pyc
designer_cmd/utils/__pycache__/utils.cpython-38.pyc
designer_cmd-0.2.18.dist-info/LICENSE.txt
designer_cmd-0.2.18.dist-info/METADATA
designer_cmd-0.2.18.dist-info/WHEEL
designer_cmd-0.2.18.dist-info/top_level.txt
designer_cmd-0.2.18.dist-info/RECORD
