Metadata-Version: 2.1
Name: designer-cmd
Version: 0.2.18
Summary: Пакет для автоматизации взаимодействия с пакетным режимом 1С.
Home-page: https://github.com/AlexanderNiMo/designer_cmd
Author: Alexander_NiMo
Author-email: binipox@gmail.com
License: MIT
Platform: Windows
Classifier: Intended Audience :: Developers
Classifier: Natural Language :: Russian
Classifier: Operating System :: Microsoft :: Windows
Classifier: Programming Language :: Python :: 3.6
Classifier: Programming Language :: Python :: Implementation :: CPython
Requires-Python: >=3.6
License-File: LICENSE.txt
